hmcode/__init__.py
hmcode/camb_stuff.py
hmcode/constants.py
hmcode/cosmology.py
hmcode/hmcode.py
hmcode/linear_growth.py
hmcode/utility.py
hmcode-1.1.1.dist-info/LICENSE
hmcode-1.1.1.dist-info/METADATA
hmcode-1.1.1.dist-info/WHEEL
hmcode-1.1.1.dist-info/RECORD
