Metadata-Version: 2.1
Name: hmcode
Version: 1.1.1
Summary: Pure Python implementation of HMcode
Home-page: https://github.com/alexander-mead/HMcode-python
License: MIT
Author: Alexander Mead
Author-email: alexander.j.mead@googlemail.com
Requires-Python: >=3.9,<3.13
Classifier: License :: OSI Approved :: MIT License
Classifier: Programming Language :: Python :: 3
Classifier: Programming Language :: Python :: 3.9
Classifier: Programming Language :: Python :: 3.10
Classifier: Programming Language :: Python :: 3.11
Classifier: Programming Language :: Python :: 3.12
Requires-Dist: camb (>=1.4.0,<2.0.0)
Requires-Dist: numpy (>=1.24.2,<2.0.0)
Requires-Dist: pyhalomodel (>=1.0.2,<2.0.0)
Requires-Dist: scipy (>=1.10.1,<2.0.0)
Project-URL: Repository, https://github.com/alexander-mead/HMcode-python
